sensirion_i2c_sen5x/__init__.py
sensirion_i2c_sen5x/device.py
sensirion_i2c_sen5x/measured_values.py
sensirion_i2c_sen5x/response_types.py
sensirion_i2c_sen5x/version.py
sensirion_i2c_sen5x/commands/__init__.py
sensirion_i2c_sen5x/commands/generated.py
sensirion_i2c_sen5x/commands/wrapped.py
sensirion_i2c_sen5x-0.1.1.dist-info/LICENSE
sensirion_i2c_sen5x-0.1.1.dist-info/METADATA
sensirion_i2c_sen5x-0.1.1.dist-info/WHEEL
sensirion_i2c_sen5x-0.1.1.dist-info/top_level.txt
sensirion_i2c_sen5x-0.1.1.dist-info/RECORD
